[
  {
    "question": "Who is the strongest?",
    "answers": {
      "a": "Superman",
      "b": "The Terminator",
      "c": "Waluigi, obviously"
    },
    "correctAnswer": "c"
  },
  {
    "question": "Who is the strongest?",
    "answers": {
      "a": "Superman",
      "b": "The Terminator",
      "c": "Waluigi, obviously"
    },
    "correctAnswer": "c"
  },
  {
    "question": "Who is the strongest?",
    "answers": {
      "a": "Superman",
      "b": "The Terminator",
      "c": "Waluigi, obviously"
    },
    "correctAnswer": "c"
  }
]
